c_module/__init__.py
c_module/main.py
c_module/cli/__init__.py
c_module/cli/cli.py
c_module/data/input/additional_information/carbon_additional_information.pkl
c_module/data/input/additional_information/carbon_additional_information.xlsx
c_module/data/input/additional_information/country_data.csv
c_module/data/input/projection_data/default_Sc_forest.csv
c_module/data/input/projection_data/default_Sc_results.csv
c_module/data/input/projection_data/default_Sc_results.pkl
c_module/data_management/__init__.py
c_module/data_management/data_manager.py
c_module/data_management/process_manager.py
c_module/logic/__init__.py
c_module/logic/base_logger.py
c_module/logic/carbon_calc.py
c_module/logic/main.py
c_module/logic/visualisation.py
c_module/parameters/__init__.py
c_module/parameters/defines.py
c_module/parameters/paths.py
c_module/user_io/__init__.py
c_module/user_io/default_parameters.py
carbon_module-1.1.2.dist-info/licenses/COPYING
carbon_module-1.1.2.dist-info/METADATA
carbon_module-1.1.2.dist-info/WHEEL
carbon_module-1.1.2.dist-info/entry_points.txt
carbon_module-1.1.2.dist-info/top_level.txt
carbon_module-1.1.2.dist-info/zip-safe
carbon_module-1.1.2.dist-info/RECORD
