Metadata-Version: 2.4
Name: Carbon-Module
Version: 1.1.2
Summary: The C-Module tracks global carbon stocks and stock changes across pools of the forestry sector, displaying them interactively
Author-email: Tomke Honkomp <tomke.honkomp@thuenen.de>
License-Expression: AGPL-3.0-or-later
Project-URL: Homepage, https://github.com/TI-Forest-Sector-Modelling
Project-URL: Documentation, https://placeholder.com
Project-URL: Repository, https://github.com/TI-Forest-Sector-Modelling/C-Module
Project-URL: Issues, https://github.com/TI-Forest-Sector-Modelling/C-Module/issues
Keywords: forestry,climate change,carbon accounting,land use change,climate change mitigation,wood products,forest sector modelling
Classifier: Programming Language :: Python :: 3
Classifier: Programming Language :: Python :: 3 :: Only
Classifier: Operating System :: Microsoft :: Windows
Classifier: Operating System :: Microsoft :: Windows :: Windows 10
Classifier: Operating System :: MacOS :: MacOS X
Classifier: Operating System :: POSIX :: Linux
Classifier: Intended Audience :: Science/Research
Classifier: Topic :: Scientific/Engineering
Requires-Python: >=3.9
License-File: COPYING
Requires-Dist: click==8.1.7
Requires-Dist: coverage==7.6.3
Requires-Dist: DateTime==5.5
Requires-Dist: dash==3.0.0
Requires-Dist: dash-bootstrap-components==2.0.0
Requires-Dist: numpy==1.26.4
Requires-Dist: openpyxl==3.1.5
Requires-Dist: pandas==1.5.3
Requires-Dist: pathlib==1.0.1
Requires-Dist: plotly==6.0.1
Requires-Dist: seaborn==0.13.2
Requires-Dist: selenium==4.2.0
Requires-Dist: tqdm==4.67.1
Requires-Dist: tomli==2.0.2
Requires-Dist: typing==3.7.4.3
Provides-Extra: dev
Requires-Dist: dash[testing]; extra == "dev"
Requires-Dist: coverage; extra == "dev"
Requires-Dist: webdriver-manager; extra == "dev"
Dynamic: license-file
